repilot/__init__.py
repilot/tool.py
repilot/utils/__init__.py
repilot/utils/schema_utils.py
repilot_client-0.1.2.dist-info/METADATA
repilot_client-0.1.2.dist-info/WHEEL
repilot_client-0.1.2.dist-info/RECORD
