Metadata-Version: 2.1
Name: repilot-client
Version: 0.1.2
Summary: 
Author: Zhixuan Lai
Author-email: zhixuan@repilot.ai
Requires-Python: >=3.8,<4.0
Classifier: Programming Language :: Python :: 3
Classifier: Programming Language :: Python :: 3.8
Classifier: Programming Language :: Python :: 3.9
Classifier: Programming Language :: Python :: 3.10
Classifier: Programming Language :: Python :: 3.11
Requires-Dist: pydantic (>=1.10.7,<2.0.0)
